dglbots/Client.py
dglbots/__init__.py
dgl_bots.py-1.1.0.dist-info/METADATA
dgl_bots.py-1.1.0.dist-info/WHEEL
dgl_bots.py-1.1.0.dist-info/top_level.txt
dgl_bots.py-1.1.0.dist-info/RECORD
