Metadata-Version: 2.1
Name: dgl-bots.py
Version: 1.1.0
Summary: A python wrapper for https://bots.discord.gl
Home-page: https://github.com/discord-gl/dgl-bots.py
Author: Piyush Bhangale
License: MIT
Project-URL: Issue tracker, https://github.com/discord-gl/dgl-bots.py/issues
Platform: UNKNOWN
Classifier: Development Status :: 5 - Production/Stable
Classifier: License :: OSI Approved :: MIT License
Classifier: Intended Audience :: Developers
Classifier: Natural Language :: English
Classifier: Operating System :: OS Independent
Classifier: Programming Language :: Python :: 3.5
Classifier: Programming Language :: Python :: 3.6
Classifier: Programming Language :: Python :: 3.7
Classifier: Topic :: Internet
Classifier: Topic :: Software Development :: Libraries
Classifier: Topic :: Software Development :: Libraries :: Python Modules
Classifier: Topic :: Utilities
Requires-Python: >=3.5.3
Requires-Dist: aiohttp
